{
    "BaseSpDef": 60,
    "Learnset": [
        "ねばねばネット",
        "すいとる",
        "れんぞくぎり",
        "エレキネット",
        "むしくい",
        "いとをはく",
        "でんじは",
        "エレキボール",
        "こうそくいどう",
        "ふいうち",
        "きりさく",
        "ほうでん",
        "いやなおと",
        "いえき",
        "むしのさざめき",
        "ミサイルばり",
        "はかいこうせん",
        "ギガインパクト",
        "ひかりのかべ",
        "ねむる",
        "どろぼう",
        "いびき",
        "まもる",
        "ギガドレイン",
        "メロメロ",
        "あまごい",
        "からげんき",
        "スピードスター",
        "とびはねる",
        "スピードスワップ",
        "クロスポイズン",
        "りんしょう",
        "ボルトチェンジ",
        "10まんボルト",
        "かみなり",
        "きゅうけつ",
        "みがわり",
        "こらえる",
        "ねごと",
        "どくづき",
        "シザークロス",
        "エナジーボール",
        "ワイルドボルト",
        "じごくづき",
        "どくばり",
        "かげぶんしん",
        "むしのていこう",
        "まとわりつく",
        "とびかかる",
        "ライジングボルト",
        "はいよるいちげき"
    ],
    "BaseSpAtk": 97,
    "NormalAbilities": [
        "ふくがん",
        "きんちょうかん"
    ],
    "Height": 0.8,
    "Weight": 14.3,
    "BaseDef": 60,
    "HiddenAbility": "むしのしらせ",
    "BaseAtk": 77,
    "Category": "通常ポケモン",
    "BaseSpeed": 108,
    "EggGroups": [
        "虫"
    ],
    "AllAbilities": [
        "ふくがん",
        "きんちょうかん",
        "むしのしらせ"
    ],
    "Types": [
        "むし",
        "でんき"
    ],
    "BaseHP": 70,
    "Gender": "♂♀両方"
}